{
  "log": {
    "level": "error",
    "timestamp": true
  },
  "dns": {
    "servers": [
      {
        "tag": "local",
        "address": "223.5.5.5",
        "detour": "direct"
      },
      {
        "tag": "remote",
        "address": "fakeip"
      }
    ],
    "rules": [
      {
        "domain_suffix": [
          ".bopufund.com",
          ".ftiasch.xyz",
          ".limao.tech"
        ],
        "server": "local"
      },
      {
        "outbound": "any",
        "server": "local"
      },
      {
        "query_type": [
          "A",
          "AAAA"
        ],
        "server": "remote"
      }
    ],
    "fakeip": {
      "enabled": true,
      "inet4_range": "198.18.0.0/15",
      "inet6_range": "fc00::/18"
    },
    "independent_cache": true
  },
  "inbounds": [
    {
      "type": "direct",
      "tag": "dns-in",
      "listen": "::",
      "listen_port": 53,
      "network": "udp",
      "override_address": "1.0.0.1",
      "override_port": 53
    },
    {
      "type": "tun",
      "tag": "tun-in",
      "mtu": 1492,
      "inet4_address": "172.19.0.1/30",
      "inet6_address": "fdfe:dcba:9876::1/126",
      "auto_route": true,
      "strict_route": true,
      "stack": "system",
      "sniff": true
    },
    {
      "type": "http",
      "tag": "http-in",
      "listen": "::",
      "listen_port": 8001
    }
  ],
  "route": {
    "rules": [
      {
        "inbound": "dns-in",
        "outbound": "dns-out"
      },
      {
        "source_ip_cidr": "172.18.0.10",
        "outbound": "direct"
      },
      {
        "type": "logical",
        "mode": "and",
        "rules": [
          {
            "rule_set": "geoip-cn",
            "invert": true
          },
          {
            "rule_set": "geosite-geolocation-!cn"
          }
        ],
        "outbound": "proxy"
      },
      {
        "type": "logical",
        "mode": "and",
        "rules": [
          {
            "rule_set": "geosite-geolocation-!cn",
            "invert": true
          },
          {
            "rule_set": [
              "geoip-cn",
              "geosite-cn",
              "geosite-category-companies@cn"
            ]
          }
        ],
        "outbound": "direct"
      },
      {
        "ip_is_private": true,
        "outbound": "direct"
      }
    ],
    "rule_set": [
      {
        "type": "remote",
        "tag": "geoip-cn",
        "format": "binary",
        "url": "https://raw.githubusercontent.com/SagerNet/sing-geoip/rule-set/geoip-cn.srs"
      },
      {
        "type": "remote",
        "tag": "geosite-cn",
        "format": "binary",
        "url": "https://raw.githubusercontent.com/SagerNet/sing-geosite/rule-set/geosite-cn.srs"
      },
      {
        "type": "remote",
        "tag": "geosite-geolocation-!cn",
        "format": "binary",
        "url": "https://raw.githubusercontent.com/SagerNet/sing-geosite/rule-set/geosite-geolocation-!cn.srs"
      },
      {
        "type": "remote",
        "tag": "geosite-category-companies@cn",
        "format": "binary",
        "url": "https://raw.githubusercontent.com/SagerNet/sing-geosite/rule-set/geosite-category-companies@cn.srs"
      }
    ],
    "final": "proxy",
    "auto_detect_interface": true
  },
  "experimental": {
    "cache_file": {
      "enabled": true,
      "path": "cache.db"
    },
    "clash_api": {
      "external_ui": "/usr/share/yacd",
      "external_controller": "0.0.0.0:9090"
    }
  }
}
